async_itertools/__init__.py
async_itertools/_version.py
async_itertools/_wrapping/__init__.py
async_itertools/_wrapping/as_async.py
async_itertools-0.0.1.dist-info/LICENSE
async_itertools-0.0.1.dist-info/METADATA
async_itertools-0.0.1.dist-info/WHEEL
async_itertools-0.0.1.dist-info/top_level.txt
async_itertools-0.0.1.dist-info/RECORD
